powerbot_asyncio_client/__init__.py
powerbot_asyncio_client/api/__init__.py
powerbot_asyncio_client/api/alert_api.py
powerbot_asyncio_client/api/algorithms_api.py
powerbot_asyncio_client/api/auction_configuration_api.py
powerbot_asyncio_client/api/auction_exchange_api.py
powerbot_asyncio_client/api/auction_order_api.py
powerbot_asyncio_client/api/auction_settings_api.py
powerbot_asyncio_client/api/auction_trade_api.py
powerbot_asyncio_client/api/auctions_api.py
powerbot_asyncio_client/api/authentication_api.py
powerbot_asyncio_client/api/capacities_api.py
powerbot_asyncio_client/api/contract_api.py
powerbot_asyncio_client/api/historic_data_api.py
powerbot_asyncio_client/api/logs_api.py
powerbot_asyncio_client/api/market_api.py
powerbot_asyncio_client/api/messages_api.py
powerbot_asyncio_client/api/orders_api.py
powerbot_asyncio_client/api/portfolios_api.py
powerbot_asyncio_client/api/report_api.py
powerbot_asyncio_client/api/schema_api.py
powerbot_asyncio_client/api/settings_api.py
powerbot_asyncio_client/api/signals_api.py
powerbot_asyncio_client/api/sso_api.py
powerbot_asyncio_client/api/subscriptions_api.py
powerbot_asyncio_client/api/tenants_api.py
powerbot_asyncio_client/api/trades_api.py
powerbot_asyncio_client/api_client.py
powerbot_asyncio_client/configuration.py
powerbot_asyncio_client/exceptions.py
powerbot_asyncio_client/models/__init__.py
powerbot_asyncio_client/models/aggregated_order_book.py
powerbot_asyncio_client/models/aggregated_order_books.py
powerbot_asyncio_client/models/aggressor_indicator.py
powerbot_asyncio_client/models/alert.py
powerbot_asyncio_client/models/alert_notification_policy.py
powerbot_asyncio_client/models/algo_command.py
powerbot_asyncio_client/models/algo_details.py
powerbot_asyncio_client/models/algo_event.py
powerbot_asyncio_client/models/algo_heartbeat.py
powerbot_asyncio_client/models/algo_image_repository.py
powerbot_asyncio_client/models/algo_instance.py
powerbot_asyncio_client/models/algo_instance_change.py
powerbot_asyncio_client-2.27.10.dist-info/METADATA
powerbot_asyncio_client-2.27.10.dist-info/WHEEL
powerbot_asyncio_client-2.27.10.dist-info/RECORD
